LICENSE
MANIFEST.in
README.md
setup.cfg
setup.py
docums_simple_hooks/__init__.py
docums_simple_hooks.egg-info/PKG-INFO
docums_simple_hooks.egg-info/SOURCES.txt
docums_simple_hooks.egg-info/dependency_links.txt
docums_simple_hooks.egg-info/entry_points.txt
docums_simple_hooks.egg-info/not-zip-safe
docums_simple_hooks.egg-info/requires.txt
docums_simple_hooks.egg-info/top_level.txt