Metadata-Version: 2.1
Name: docums-simple-hooks
Version: 0.1.5
Summary: Define your own hooks for docums, without having to create a new package.
Home-page: https://github.com/khanhduy1407/docums-simple-hooks
Author: NKDuy
Author-email: kn145660@gmail.com
License: MIT
Platform: UNKNOWN
Classifier: Programming Language :: Python :: 3
Classifier: Programming Language :: Python :: 3.6
Classifier: Programming Language :: Python :: 3.7
Classifier: Programming Language :: Python :: 3.8
Classifier: Programming Language :: Python :: 3.9
Classifier: Programming Language :: Python :: 3.10
Classifier: License :: OSI Approved :: MIT License
Classifier: Operating System :: OS Independent
Classifier: Intended Audience :: Developers
Classifier: Topic :: Documentation
Provides-Extra: test
